asgi_plausible.py
asgi_plausible-0.1.dist-info/METADATA
asgi_plausible-0.1.dist-info/WHEEL
asgi_plausible-0.1.dist-info/licenses/LICENSE
asgi_plausible-0.1.dist-info/RECORD
